marvel_schedule_maker/__init__.py
marvel_schedule_maker/__main__.py
marvel_schedule_maker/__version__.py
marvel_schedule_maker/main.py
marvel_schedule_maker/assets/OBJECT_CATALOG.json
marvel_schedule_maker/assets/icon.png
marvel_schedule_maker/assets/splash.png
marvel_schedule_maker/config/units/unit1.cfg
marvel_schedule_maker/config/units/unit2.cfg
marvel_schedule_maker/config/units/unit3.cfg
marvel_schedule_maker/config/units/unit4.cfg
marvel_schedule_maker/models/ActionContext.py
marvel_schedule_maker/models/ActionFieldModel.py
marvel_schedule_maker/models/ActionPanelUIConfig.py
marvel_schedule_maker/models/ActionRegistry.py
marvel_schedule_maker/models/CelestialObjectModel.py
marvel_schedule_maker/models/NotificationTypes.py
marvel_schedule_maker/models/ObservationDateModel.py
marvel_schedule_maker/models/ScheduleModel.py
marvel_schedule_maker/models/TaskRectUIConfig.py
marvel_schedule_maker/models/Timeline.py
marvel_schedule_maker/models/TimelinePanelUIConfig.py
marvel_schedule_maker/repository/CelestialObjectRepository.py
marvel_schedule_maker/services/ApplicationServices.py
marvel_schedule_maker/utils/Astronomy.py
marvel_schedule_maker/utils/LocationConfig.py
marvel_schedule_maker/utils/TelescopeConfig.py
marvel_schedule_maker/utils/sequencer.py
marvel_schedule_maker/utils/svg_renderers.py
marvel_schedule_maker/viewmodels/ActionPanelViewModel.py
marvel_schedule_maker/viewmodels/CelestialObjectViewModel.py
marvel_schedule_maker/viewmodels/MainWindowViewModel.py
marvel_schedule_maker/viewmodels/NotificationViewModel.py
marvel_schedule_maker/viewmodels/SolarCycleBarViewModel.py
marvel_schedule_maker/viewmodels/TimelinePanelViewModel.py
marvel_schedule_maker/viewmodels/TopBarViewModel.py
marvel_schedule_maker/viewmodels/actionpanelviewmodels/ActionPickerViewModel.py
marvel_schedule_maker/viewmodels/actionpanelviewmodels/InputFormViewModel.py
marvel_schedule_maker/viewmodels/actionpanelviewmodels/ObserveGraphViewModel.py
marvel_schedule_maker-2.1.3.dist-info/licenses/LICENSE
marvel_schedule_maker-2.1.3.dist-info/METADATA
marvel_schedule_maker-2.1.3.dist-info/WHEEL
marvel_schedule_maker-2.1.3.dist-info/entry_points.txt
marvel_schedule_maker-2.1.3.dist-info/top_level.txt
marvel_schedule_maker-2.1.3.dist-info/RECORD
