Metadata-Version: 2.4
Name: marvel_schedule_maker
Version: 2.1.3
Summary: Marvel Schedule Maker - Telescope observation scheduling application
Author-email: YheoS <yheo99@gmail.com>
Requires-Python: >=3.9
License-File: LICENSE
Requires-Dist: PyQt6>=6.10.0
Requires-Dist: qtawesome>=1.4.0
Requires-Dist: pandas>=2.3.3
Requires-Dist: astropy>=7.2.0
Requires-Dist: astroplan>=0.10.1
Requires-Dist: numpy>=2.3.5
Requires-Dist: pyqtgraph>=0.14.0
Dynamic: license-file
